torchada/__init__.py
torchada/_mapping.py
torchada/_patch.py
torchada/_platform.py
torchada/cuda/__init__.py
torchada/cuda/amp.py
torchada/cuda/nvtx.py
torchada/utils/__init__.py
torchada/utils/cpp_extension.py
torchada-0.1.15.dist-info/LICENSE
torchada-0.1.15.dist-info/METADATA
torchada-0.1.15.dist-info/WHEEL
torchada-0.1.15.dist-info/top_level.txt
torchada-0.1.15.dist-info/RECORD
