Metadata-Version: 2.1
Name: torchada
Version: 0.1.15
Summary: Adapter package for torch_musa to act exactly like PyTorch CUDA
Author: torchada contributors
License: MIT
Project-URL: Homepage, https://github.com/MooreThreads/torchada
Project-URL: Repository, https://github.com/MooreThreads/torchada
Keywords: pytorch,cuda,musa,moore-threads,gpu,adapter
Classifier: Development Status :: 4 - Beta
Classifier: Intended Audience :: Developers
Classifier: Intended Audience :: Science/Research
Classifier: License :: OSI Approved :: MIT License
Classifier: Programming Language :: Python :: 3
Classifier: Programming Language :: Python :: 3.8
Classifier: Programming Language :: Python :: 3.9
Classifier: Programming Language :: Python :: 3.10
Classifier: Programming Language :: Python :: 3.11
Classifier: Programming Language :: Python :: 3.12
Classifier: Topic :: Scientific/Engineering :: Artificial Intelligence
Requires-Python: >=3.8
License-File: LICENSE
Requires-Dist: torch
Provides-Extra: dev
Requires-Dist: pytest; extra == "dev"
Requires-Dist: pytest-cov; extra == "dev"
Requires-Dist: black; extra == "dev"
Requires-Dist: isort; extra == "dev"
Requires-Dist: mypy; extra == "dev"
Provides-Extra: musa
Requires-Dist: torch-musa; extra == "musa"
